config42/__init__.py
config42/__main__.py
config42/config_manager.py
config42/init_apps.py
config42/utils.py
config42/validator.py
config42/handlers/__init__.py
config42/handlers/argparse.py
config42/handlers/base.py
config42/handlers/environment.py
config42/handlers/etcd.py
config42/handlers/file.py
config42/handlers/memory.py
config42/handlers/raw.py
config42/handlers/files/__init__.py
config42/handlers/files/base.py
config42/handlers/files/ini.py
config42/handlers/files/json.py
config42/handlers/files/yaml.py
config42-0.4.4.dist-info/COPYING
config42-0.4.4.dist-info/METADATA
config42-0.4.4.dist-info/WHEEL
config42-0.4.4.dist-info/entry_points.txt
config42-0.4.4.dist-info/top_level.txt
config42-0.4.4.dist-info/RECORD
