Metadata-Version: 2.1
Name: config42
Version: 0.4.4
Summary: Configuration manager for cloud native application, support configuration  stored in memory, in files, in databases
Home-page: https://github.com/yurilaaziz/config42
Author: Amine Ben Asker
Author-email: ben.asker.amine@gmail.com
License: GPLv3+
Download-URL: https://github.com/yurilaaziz/config42/releases/tag/0.2
Keywords: Pretty configuration manager,Key value data store,cloud native configuration
Platform: UNKNOWN
Classifier: Development Status :: 5 - Production/Stable
Classifier: Intended Audience :: Developers
Classifier: Topic :: Software Development :: Build Tools
Classifier: License :: OSI Approved :: MIT License
Classifier: Programming Language :: Python :: 3
Classifier: Programming Language :: Python :: 3.4
Classifier: Programming Language :: Python :: 3.5
Classifier: Programming Language :: Python :: 3.6
Classifier: Programming Language :: Python :: 3.7
Requires-Dist: Pyyaml (>=5.1)
Requires-Dist: Jinja2 (>=2.0)
Requires-Dist: Cerberus (>=1.3.1)
